buildpost/__init__.py
buildpost/cli.py
buildpost/core/__init__.py
buildpost/core/ai_service.py
buildpost/core/git_parser.py
buildpost/core/prompt_engine.py
buildpost/templates/prompts.yaml
buildpost/utils/__init__.py
buildpost/utils/config.py
buildpost/utils/formatters.py
buildpost/utils/token_resolver.py
buildpost-0.1.2.dist-info/licenses/LICENSE
buildpost-0.1.2.dist-info/METADATA
buildpost-0.1.2.dist-info/WHEEL
buildpost-0.1.2.dist-info/entry_points.txt
buildpost-0.1.2.dist-info/top_level.txt
buildpost-0.1.2.dist-info/RECORD
