Metadata-Version: 2.4
Name: buildpost
Version: 0.1.2
Summary: Turn your git commits into social media posts using AI
Home-page: https://github.com/sharonibejih/buildpost
Author: BuildPost Team
Author-email: ebulamicheal@gmail.com
Project-URL: Bug Reports, https://github.com/sharonibejih/buildpost/issues
Project-URL: Source, https://github.com/sharonibejih/buildpost
Classifier: Development Status :: 3 - Alpha
Classifier: Intended Audience :: Developers
Classifier: Topic :: Software Development :: Version Control :: Git
Classifier: License :: OSI Approved :: MIT License
Classifier: Programming Language :: Python :: 3
Classifier: Programming Language :: Python :: 3.8
Classifier: Programming Language :: Python :: 3.9
Classifier: Programming Language :: Python :: 3.10
Classifier: Programming Language :: Python :: 3.11
Requires-Python: >=3.8
License-File: LICENSE
Requires-Dist: click>=8.0.0
Requires-Dist: gitpython>=3.1.0
Requires-Dist: pyyaml>=6.0
Requires-Dist: openai>=1.0.0
Requires-Dist: groq>=0.8.0
Requires-Dist: pyperclip>=1.8.0
Requires-Dist: colorama>=0.4.6
Requires-Dist: rich>=13.0.0
Dynamic: author
Dynamic: author-email
Dynamic: classifier
Dynamic: description
Dynamic: description-content-type
Dynamic: home-page
Dynamic: license-file
Dynamic: project-url
Dynamic: requires-dist
Dynamic: requires-python
Dynamic: summary
